{
  "name": "Euclid MCP Multi-Project Dev Environment",
  "build": {
    "dockerfile": "Dockerfile",
    "context": "."
  },
  "customizations": {
    "vscode": {
      "extensions": [
        "ms-python.python",
        "ms-python.vscode-pylance",
        "ms-python.black-formatter",
        "ms-python.isort",
        "ms-python.flake8",
        "charliermarsh.ruff",
        "tamasfe.even-better-toml",
        "redhat.vscode-yaml"
      ],
      "settings": {
        "python.defaultInterpreterPath": "/usr/local/bin/python",
        "python.formatting.provider": "none",
        "python.linting.enabled": true,
        "python.linting.flake8Enabled": true,
        "editor.formatOnSave": true,
        "editor.codeActionsOnSave": {
          "source.organizeImports": "explicit"
        },
        "[python]": {
          "editor.defaultFormatter": "ms-python.black-formatter"
        },
        "files.exclude": {
          "**/.git": false,
          "**/__pycache__": true,
          "**/*.pyc": true
        }
      }
    }
  },
  "remoteUser": "root",
  "mounts": [
    "source=${localEnv:HOME}/.ssh,target=/root/.ssh,readonly,type=bind,consistency=cached",
    "source=/media/aaron/DATA,target=/data,readonly,type=bind,consistency=cached"
  ],
  "forwardPorts": [],
  "runArgs": [
    "--network=host"
  ]
}